serverless_env
