Metadata-Version: 1.1
Name: serverless-env
Version: 0.2
Summary: Helper functions for Serverless
Home-page: http://github.com/cscetbon/serverless-helpers-py
Author: Cyril Scetbon
Author-email: cscetbon@xxxx.com
License: BSD
Platform: UNKNOWN
Classifier: Programming Language :: Python :: 2.7
Classifier: Programming Language :: Python :: 3
Classifier: Programming Language :: Python :: 3.3
Classifier: Programming Language :: Python :: 3.4
Classifier: Programming Language :: Python :: 3.5
